fast_forward/__init__.py
fast_forward/py.typed
fast_forward/ranking.py
fast_forward/docs/encoder.md
fast_forward/docs/index.md
fast_forward/docs/indexer.md
fast_forward/docs/main.md
fast_forward/docs/pyterrier.md
fast_forward/docs/quantizer.md
fast_forward/docs/ranking.md
fast_forward/docs/util.md
fast_forward/encoder/__init__.py
fast_forward/encoder/base.py
fast_forward/encoder/transformer.py
fast_forward/index/__init__.py
fast_forward/index/base.py
fast_forward/index/disk.py
fast_forward/index/memory.py
fast_forward/index/util.py
fast_forward/quantizer/__init__.py
fast_forward/quantizer/base.py
fast_forward/quantizer/nanopq.py
fast_forward/util/__init__.py
fast_forward/util/indexer.py
fast_forward/util/pyterrier.py
fast_forward_indexes-0.8.0.dist-info/licenses/LICENSE
fast_forward_indexes-0.8.0.dist-info/METADATA
fast_forward_indexes-0.8.0.dist-info/WHEEL
fast_forward_indexes-0.8.0.dist-info/top_level.txt
fast_forward_indexes-0.8.0.dist-info/RECORD
