Metadata-Version: 2.4
Name: fast-forward-indexes
Version: 0.8.0
Summary: Efficient interpolation-based ranking on CPUs
Author: Jurek Leonhardt
License: MIT License
Project-URL: Repository, https://github.com/mrjleo/fast-forward-indexes
Project-URL: Documentation, https://mrjleo.github.io/fast-forward-indexes/docs/
Keywords: information retrieval,ranking,search
Classifier: Programming Language :: Python :: 3
Classifier: License :: OSI Approved :: MIT License
Classifier: Intended Audience :: Science/Research
Requires-Python: <3.14,>=3.10
License-File: LICENSE
Requires-Dist: torch<3,>=2.0.0
Requires-Dist: numpy<2,>=1.24.0
Requires-Dist: pandas<3,>=2.0.3
Requires-Dist: transformers<5,>=4.28.0
Requires-Dist: h5py<4,>=3.0.0
Requires-Dist: tqdm<5,>=4.66.0
Requires-Dist: nanopq<0.3,>=0.2.1
Provides-Extra: pyterrier
Requires-Dist: python-terrier<0.13,>=0.12.0; extra == "pyterrier"
Dynamic: license-file
